dspf/__init__.py
dspf/__main__.py
dspf/factor_analysis.py
dspf/py.typed
dspf/utils/__init__.py
dspf/utils/fa_utils.py
dspf/visualization/__init__.py
dspf/visualization/fa_visualization.py
dspf-0.0.1a6.dist-info/entry_points.txt
dspf-0.0.1a6.dist-info/LICENSE
dspf-0.0.1a6.dist-info/WHEEL
dspf-0.0.1a6.dist-info/METADATA
dspf-0.0.1a6.dist-info/RECORD
