Metadata-Version: 2.1
Name: dspf
Version: 0.0.1a6
Summary: Data Science Portfolio
Home-page: https://github.com/MoritzM00/data-science-portfolio
License: MIT
Author: Moritz Mistol
Author-email: moritz.mistol@gmail.com
Requires-Python: >=3.8,<3.12
Classifier: Development Status :: 1 - Planning
Classifier: License :: OSI Approved :: MIT License
Classifier: Programming Language :: Python :: 3
Classifier: Programming Language :: Python :: 3.8
Classifier: Programming Language :: Python :: 3.9
Classifier: Programming Language :: Python :: 3.10
Requires-Dist: click (>=8.0.1)
Requires-Dist: factor_analyzer (>=0.4.0)
Requires-Dist: matplotlib (>=3.5.3)
Requires-Dist: numpy (>=1.23.2)
Requires-Dist: pandas (>=1.4.3)
Requires-Dist: scikit-learn (>=1.1.2)
Requires-Dist: scipy (>=1.9.0)
Requires-Dist: seaborn (>=0.11.2)
Project-URL: Changelog, https://github.com/MoritzM00/data-science-portfolio/releases
Project-URL: Documentation, https://dspf.readthedocs.io
Project-URL: Repository, https://github.com/MoritzM00/data-science-portfolio
